{
  "project_info": {
    "project_number": "838079767924",
    "project_id": "dmsproject-99d8e",
    "storage_bucket": "dmsproject-99d8e.appspot.com"
  },
  "client": [
    {
      "client_info": {
        "mobilesdk_app_id": "1:838079767924:android:3e703d3bdaf3bd2292b821",
        "android_client_info": {
          "package_name": "com.example.flutter_project"
        }
      },
      "oauth_client": [
        {
          "client_id": "838079767924-0qhrukk6tstchurkqh6fuunek4cpt5gq.apps.googleusercontent.com",
          "client_type": 1,
          "android_info": {
            "package_name": "com.example.flutter_project",
            "certificate_hash": "223415f4b6992874fc29a730f3d6d809087d3de9"
          }
        },
        {
          "client_id": "838079767924-l0j05ldvuscrjvm1gnl2luk95c0dcu5c.apps.googleusercontent.com",
          "client_type": 3
        }
      ],
      "api_key": [
        {
          "current_key": "AIzaSyA4G1aX4OGLZh4RzDNiLUUY5yiFjRMeWSU"
        }
      ],
      "services": {
        "appinvite_service": {
          "other_platform_oauth_client": [
            {
              "client_id": "838079767924-l0j05ldvuscrjvm1gnl2luk95c0dcu5c.apps.googleusercontent.com",
              "client_type": 3
            },
            {
              "client_id": "838079767924-5q3hgepmsl1e278hlo3lcb3c50semdj8.apps.googleusercontent.com",
              "client_type": 2,
              "ios_info": {
                "bundle_id": "com.example.flutterProject"
              }
            }
          ]
        }
      }
    }
  ],
  "configuration_version": "1"
}